Workbook

Sheet Revenue Quality
A1: KO Investment Analysis — Revenue Quality
A2: Source: KO 10-K filings for FY ended 12/31/2022, 12/31/2023, 12/31/2024. All $ figures in millions unless noted.
A4: SECTION 1: VOLUME vs. PRICE/MIX DECOMPOSITION
B5: FY2022 | C5: FY2023 | D5: FY2024 | F5: Source / Filing Reference
A6: Reported Net Revenue ($mm) | B6: 43004 | C6: 45754 | D6: 47061 | F6: 10-K, Consolidated Stmt of Income, each FY
A7: Net Revenue Growth (YoY) | B7: n/a | C7: =((C6-B6)/B6) -> 0.06394754 | D7: =((D6-C6)/C6) -> 0.028565808 | F7: Calculated: (Current - Prior) / Prior
A8: Organic Revenue Growth (non-GAAP) | B8: 0.16 | C8: 0.12 | D8: 0.12 | F8: 10-K Item 7, MD&A Operating Review, each FY
A10: Unit Case Volume Growth | B10: 0.05 | C10: 0.02 | D10: 0.01 | F10: 10-K Item 7, MD&A Operating Review, each FY
A11: Concentrate Sales Growth | B11: 0.04 | C11: 0.02 | D11: 0.02 | F11: 10-K Item 7, MD&A / Earnings Release revenue bridge
A12: Price/Mix Growth | B12: 0.11 | C12: 0.1 | D12: 0.11 | F12: 10-K Item 7, MD&A / Earnings Release revenue bridge
A13: Currency Impact | B13: -0.07 | C13: -0.04 | D13: -0.05 | F13: 10-K Item 7, MD&A / Earnings Release revenue bridge
A14: Structural Changes (Acq/Div) | B14: -0.01 | C14: -0.01 | D14: -0.04 | F14: 10-K Item 7, MD&A / Earnings Release revenue bridge
A16: Price/Mix as % of Organic Growth | B16: =B12/B8 -> 0.6875 | C16: =C12/C8 -> 0.83333333 | D16: =D12/D8 -> 0.91666667 | F16: Calculated: Price/Mix ÷ Organic Revenue Growth
A17: Volume as % of Organic Growth | B17: =B11/B8 -> 0.25 | C17: =C11/C8 -> 0.16666667 | D17: =D11/D8 -> 0.16666667 | F17: Calculated: Concentrate Sales ÷ Organic Revenue Growth
A19: Analyst Note: KO's organic growth has been overwhelmingly price/mix-driven (≈80-85% of organic growth). Volume growth is modest (1-2%) which is typical for a mature beverage company.
A20: ~5pp of price/mix in FY2024 came from hyperinflationary markets (mainly Argentina). Structural changes (refranchising of bottling ops in India, Philippines, Bangladesh) are a -4pp drag in FY2024.
A21: Filing dates: FY2024 10-K filed 2025-02-20; FY2023 10-K filed 2024-02-20; FY2022 10-K filed 2024-02-20 (comparative year in FY2023 filing).
A23: SECTION 2: GEOGRAPHIC SEGMENT NET REVENUES ($mm)
B24: FY2022 | C24: FY2023 | D24: FY2024 | F24: Source / Filing Reference
A25: Europe, Middle East & Africa | B25: 7418 | C25: 7418 | D25: 7508 | F25: 10-K, Note 20 — Operating Segments, each FY
A26: Latin America | B26: 4675 | C26: 5820 | D26: 6434 | F26: 10-K, Note 20 — Operating Segments, each FY
A27: North America | B27: 15137 | C27: 16904 | D27: 18636 | F27: 10-K, Note 20 — Operating Segments, each FY
A28: Asia Pacific | B28: 5059 | C28: 4708 | D28: 5546 | F28: 10-K, Note 20 — Operating Segments, each FY
A29: Global Ventures | B29: 2821 | C29: 3077 | D29: 3144 | F29: 10-K, Note 20 — Operating Segments, each FY
A30: Bottling Investments | B30: 7973 | C30: 7882 | D30: 5906 | F30: 10-K, Note 20 — Operating Segments, each FY
A31: Corporate & Eliminations | B31: -79 | C31: -55 | D31: -113 | F31: 10-K, Note 20 — Operating Segments, each FY
A32: Total Net Revenues | B32: =SUM(B25:B31) -> 43004 | C32: =SUM(C25:C31) -> 45754 | D32: =SUM(D25:D31) -> 47061 | F32: Sum of segments
A34: % North America | B34: =B27/B32 -> 0.35199051 | C34: =C27/C32 -> 0.36945404 | D34: =D27/D32 -> 0.39599669 | F34: Calculated
A35: % International (ex-NA) | B35: =(B25+B26+B28+B29)/B32 -> 0.46444517 | C35: =(C25+C26+C28+C29)/C32 -> 0.45947895 | D35: =(D25+D26+D28+D29)/D32 -> 0.48090776 | F35: Calculated
A36: % Bottling Investments | B36: =B30/B32 -> 0.18540136 | C36: =C30/C32 -> 0.17226909 | D36: =D30/D32 -> 0.1254967 | F36: Calculated
A39: SECTION 3: CONCENTRATE vs. FINISHED PRODUCT REVENUE MIX ($mm)
B40: FY2022 | C40: FY2023 | D40: FY2024 | F40: Source / Filing Reference
A41: Concentrate Operations Revenue | B41: 21049 | C41: 22310 | D41: 24565 | F41: 10-K, Note 20 — Revenue by product type, each FY
A42: Finished Product Operations Revenue | B42: 21955 | C42: 23444 | D42: 22496 | F42: 10-K, Note 20 — Revenue by product type, each FY
A43: Total Net Revenues | B43: =B41+B42 -> 43004 | C43: =C41+C42 -> 45754 | D43: =D41+D42 -> 47061 | F43: Sum
A45: Concentrate % of Total | B45: =B41/B43 -> 0.4894661 | C45: =C41/C43 -> 0.48760764 | D45: =D41/D43 -> 0.52198211 | F45: Calculated
A46: Finished Product % of Total | B46: =B42/B43 -> 0.5105339 | C46: =C42/C43 -> 0.51239236 | D46: =D42/D43 -> 0.47801789 | F46: Calculated
A48: Analyst Note: Concentrate operations (capital-light, high-margin) have grown from ~49% to ~52% of revenue FY22→FY24, driven by refranchising of bottling ops (India, Philippines, Bangladesh in FY24).
A49: This structural shift toward asset-light model boosts ROIC and margins over time. Finished product revenue declined in FY24 due to the divestiture of consolidated bottling operations classified as structural changes.
A50: Revenue by product type sourced from Note 20 Operating Segments in each respective 10-K filing. FY2024 concentrate = 52.2%, up from 48.9% in FY2022.
A51: FY2024 10-K filing date: 2025-02-20 (Accession: 0000021344-25-000011). FY2023 10-K filing date: 2024-02-20 (Accession: 0000021344-24-000009).

Sheet Cash Economics
A1: KO Investment Analysis — Cash Economics
A2: Source: KO 10-K filings for FY ended 12/31/2022, 12/31/2023, 12/31/2024. All $ figures in millions unless noted.
A4: SECTION 1: PROFITABILITY TO FREE CASH FLOW BRIDGE ($mm)
B5: FY2022 | C5: FY2023 | D5: FY2024 | F5: Source / Filing Reference
A6: Net Income (attributable to KO) | B6: 9542 | C6: 10714 | D6: 10631 | F6: 10-K, Consolidated Stmt of Income, each FY
A7: D&A | B7: 1260 | C7: 1128 | D7: 1075 | F7: 10-K, Consolidated Stmt of Cash Flows, each FY
A8: EBITDA (Operating) | B8: =B16+B7 -> 13601 | C8: =C16+C7 -> 12439 | D8: =D16+D7 -> 11067 | F8: Calculated: Op Income + D&A
A10: Cash Flow from Operations (CFO) | B10: 11018 | C10: 11599 | D10: 6805 | F10: 10-K, Consolidated Stmt of Cash Flows, each FY
A11: Capital Expenditures | B11: 1484 | C11: 1852 | D11: 2064 | F11: 10-K, Consolidated Stmt of Cash Flows, each FY
A12: Free Cash Flow (CFO - CapEx) | B12: =B10-B11 -> 9534 | C12: =C10-C11 -> 9747 | D12: =D10-D11 -> 4741 | F12: Calculated
A13: Memo: IRS Tax Litigation Deposit | B13: 0 | C13: 0 | D13: 6000 | F13: 10-K Item 7, MD&A / Earnings Release FY2024
A14: FCF excl. IRS Deposit | B14: =B12+B13 -> 9534 | C14: =C12+C13 -> 9747 | D14: =D12+D13 -> 10741 | F14: Calculated: FCF + IRS deposit
A16: Operating Income | B16: 12341 | C16: 11311 | D16: 9992 | F16: 10-K, Consolidated Stmt of Income, each FY
A17: EBITDA | B17: =B16+B7 -> 13601 | C17: =C16+C7 -> 12439 | D17: =D16+D7 -> 11067 | F17: Calculated: Op Income + D&A
A19: SECTION 2: CASH CONVERSION & CAPITAL INTENSITY METRICS
B20: FY2022 | C20: FY2023 | D20: FY2024 | F20: Source / Filing Reference
A21: FCF / Net Income | B21: =B12/B6 -> 0.9991616 | C21: =C12/C6 -> 0.90974426 | D21: =D12/D6 -> 0.44595993 | F21: Calculated
A22: FCF excl. IRS / Net Income | B22: =B14/B6 -> 0.9991616 | C22: =C14/C6 -> 0.90974426 | D22: =D14/D6 -> 1.0103471 | F22: Calculated — normalizes FY24 IRS deposit
A23: CFO / EBITDA | B23: =B10/B17 -> 0.81008749 | C23: =C10/C17 -> 0.93247046 | D23: =D10/D17 -> 0.61489112 | F23: Calculated
A25: CapEx / Revenue | B25: =B11/B28 -> 0.034508418 | C25: =C11/C28 -> 0.040477335 | D25: =D11/D28 -> 0.043857972 | F25: Calculated: CapEx ÷ Revenue (from Tab 1)
A26: CapEx / D&A | B26: =B11/B7 -> 1.1777778 | C26: =C11/C7 -> 1.641844 | D26: =D11/D7 -> 1.92 | F26: Calculated: investment vs. maintenance proxy
A28: Revenue ($mm — from Tab 1) | B28: ='Revenue Quality'!B6 -> 43004 | C28: ='Revenue Quality'!C6 -> 45754 | D28: ='Revenue Quality'!D6 -> 47061 | F28: Cross-sheet reference
A30: SECTION 3: CAPITAL ALLOCATION ($mm)
B31: FY2022 | C31: FY2023 | D31: FY2024 | F31: Source / Filing Reference
A32: Dividends Paid | B32: 7616 | C32: 8018 | D32: 8366 | F32: 10-K, Consolidated Stmt of Cash Flows, each FY
A33: Share Repurchases (gross) | B33: 1418 | C33: 2289 | D33: 1795 | F33: 10-K, Consolidated Stmt of Cash Flows, each FY
A34: Total Shareholder Returns | B34: =B32+B33 -> 9034 | C34: =C32+C33 -> 10307 | D34: =D32+D33 -> 10161 | F34: Sum
A35: Capital Expenditures | B35: 1484 | C35: 1852 | D35: 2064 | F35: 10-K, Consolidated Stmt of Cash Flows, each FY
A36: Acquisitions (net) | B36: 107 | C36: 4766 | D36: 48 | F36: 10-K, Consolidated Stmt of Cash Flows, each FY
A37: Total Reinvestment | B37: =B35+B36 -> 1591 | C37: =C35+C36 -> 6618 | D37: =D35+D36 -> 2112 | F37: Sum
A39: Shareholder Returns / CFO | B39: =B34/B10 -> 0.81993102 | C39: =C34/C10 -> 0.88861109 | D39: =D34/D10 -> 1.4931668 | F39: Calculated
A40: Shareholder Returns / FCF excl. IRS | B40: =B34/B14 -> 0.94755612 | C40: =C34/C14 -> 1.0574536 | D40: =D34/D14 -> 0.9460013 | F40: Calculated
A41: Dividend Payout Ratio (Div / NI) | B41: =B32/B6 -> 0.79815552 | C41: =C32/C6 -> 0.74836662 | D41: =D32/D6 -> 0.78694384 | F41: Calculated
A43: SECTION 4: WORKING CAPITAL & CASH CONVERSION CYCLE
B44: FY2022 | C44: FY2023 | D44: FY2024 | F44: Source / Filing Reference
A45: Trade Accounts Receivable | B45: 3487 | C45: 3410 | D45: 3680 | F45: 10-K, Consolidated Balance Sheet, each FY
A46: Inventories | B46: 4233 | C46: 3878 | D46: 3844 | F46: 10-K, Consolidated Balance Sheet, each FY
A47: Trade Accounts Payable | B47: 7955 | C47: 7526 | D47: 7710 | F47: 10-K, Consolidated Balance Sheet, each FY (AP + accrued liabilities)
A48: Cost of Goods Sold | B48: 18000 | C48: 18520 | D48: 18324 | F48: 10-K, Consolidated Stmt of Income, each FY
A49: Net Revenue | B49: 43004 | C49: 45754 | D49: 47061 | F49: 10-K, Consolidated Stmt of Income, each FY
A51: Days Sales Outstanding (DSO) | B51: =B45/B49*365 -> 29.5962 | C51: =C45/C49*365 -> 27.203086 | D51: =D45/D49*365 -> 28.54168 | F51: Calculated: (AR / Revenue) × 365
A52: Days Inventory Outstanding (DIO) | B52: =B46/B48*365 -> 85.835833 | C52: =C46/C48*365 -> 76.429266 | D52: =D46/D48*365 -> 76.569526 | F52: Calculated: (Inv / COGS) × 365
A53: Days Payable Outstanding (DPO) | B53: =B47/B48*365 -> 161.30972 | C53: =C47/C48*365 -> 148.32559 | D53: =D47/D48*365 -> 153.57728 | F53: Calculated: (AP / COGS) × 365
A54: Cash Conversion Cycle (CCC) | B54: =B51+B52-B53 -> -45.877689 | C54: =C51+C52-C53 -> -44.693242 | D54: =D51+D52-D53 -> -48.466069 | F54: Calculated: DSO + DIO - DPO
A56: Analyst Notes:
A57: FY2024 CFO of $6.8B includes a $6.0B deposit to the IRS for ongoing tax litigation (Sec. 7481(a)). Excluding this one-time item, normalized FCF was ~$10.7B, up ~10% YoY — consistent with KO's history of strong cash generation.
A58: Sign convention: KO presents capex as negative on the CFS (investing activities). We show it as a positive number here and subtract it from CFO to arrive at FCF.
A59: Trade AP includes 'Accounts payable and accrued expenses' per KO's balance sheet presentation. This is the most comparable metric as KO bundles these line items. CCC is negative, indicating KO funds operations on supplier credit — characteristic of concentrate model.
A60: Filing dates: FY2024 10-K filed 2025-02-20 (Accession: 0000021344-25-000011). FY2023 10-K filed 2024-02-20 (Accession: 0000021344-24-000009).
A61: FY2023 acquisitions net of $4,766mm primarily reflects fairlife LLC contingent consideration payments. FY2022 and FY2024 acquisition activity was minimal.

Sheet Valuation Context
A1: KO Investment Analysis — Valuation Context
A2: As-of 12/31/2024 close. Market data from Yahoo Finance / Twelve Data. Financials from KO 10-K FY2024 (filed 2025-02-20).
A4: SECTION 1: MARKET CAPITALIZATION & ENTERPRISE VALUE
B5: Value | D5: Source / Filing Reference
A6: Share Price (12/31/2024 close) | B6: 62.17 | D6: Yahoo Finance / Twelve Data — KO close 12/31/2024
A7: Diluted Shares Outstanding (mm) | B7: 4320 | D7: 10-K FY2024, Consolidated Stmt of Income — diluted shares
A8: Market Capitalization ($mm) | B8: =B6*B7 -> 268574.4 | D8: Calculated: Price × Diluted Shares
A10: (+) Total Debt (short + long-term) | B10: 42064 | D10: 10-K FY2024, Consolidated Balance Sheet (loans/notes payable + current maturities LTD + LT debt)
A11: (+) Minority Interest (NCI) | B11: 1539 | D11: 10-K FY2024, Consolidated Balance Sheet — NCI equity
A12: (-) Cash & Cash Equivalents | B12: 10828 | D12: 10-K FY2024, Consolidated Balance Sheet
A13: (-) Short-term Investments | B13: 3304 | D13: 10-K FY2024, Consolidated Balance Sheet — marketable securities
A14: Enterprise Value ($mm) | B14: =B8+B10+B11-B12-B13 -> 298045.4 | D14: Calculated: Mkt Cap + Debt + NCI - Cash - ST Investments
A16: Net Debt Methodology: Total Debt = current portion of long-term debt + loans/notes payable + long-term debt. Cash offset includes cash & equivalents plus short-term marketable securities.
A17: We add NCI because KO consolidates entities with minority interests. We exclude equity method investments ($19.8B) from the EV bridge as they represent ownership stakes in bottlers already captured via equity income in earnings.
A18: Total Debt breakdown: Loans & notes payable + Current maturities of LTD + Long-term debt from FY2024 Consolidated Balance Sheet.
A21: SECTION 2: VALUATION MULTIPLES (as-of 12/31/2024)
A22: Multiple | B22: Value | D22: Rationale / Source
A23: EV / EBITDA (FY2024) | B23: =B14/'Cash Economics'!D17 -> 26.931002 | D23: Core comps multiple for staples. EBITDA from Cash Economics tab.
A24: EV / EBIT (FY2024) | B24: =B14/'Cash Economics'!D16 -> 29.828403 | D24: Captures D&A differences vs. peers (PEP has higher capex).
A25: P/E — Reported (FY2024) | B25: =B8/'Cash Economics'!D6 -> 25.263324 | D25: Trailing P/E on GAAP net income.
A26: P/E — Comparable EPS (FY2024) | B26: =B6/2.88 -> 21.586806 | D26: Uses comparable EPS of $2.88 (non-GAAP) per earnings release.
A27: FCF Yield (excl. IRS deposit) | B27: ='Cash Economics'!D14/B8 -> 0.039992643 | D27: Normalized FCF / Market Cap — key for dividend sustainability.
A28: Dividend Yield | B28: =1.94/B6 -> 0.031204761 | D28: Annualized dividend of $1.94/share ÷ share price.
A30: "Why these multiples" note:
A31: EV/EBITDA is the primary comp metric for consumer staples. EV/EBIT adjusts for KO's declining D&A as it refranchises bottling ops.
A32: P/E on comparable EPS strips out one-time items (fairlife contingent consideration, BODYARMOR impairment, restructuring). FCF yield (normalized) tests whether the dividend is covered by real cash generation.
A33: Comparable EPS of $2.88 is a non-GAAP measure from KO's FY2024 earnings release. Annualized dividend of $1.94/share from KO's declared quarterly dividends in FY2024.
A35: SECTION 3: PRICE RETURN COMPARISON (not total return)
B36: 44561 | C36: 45291 | D36: 45657 | E36: Source
A37: KO Price ($) | B37: 59.21 | C37: 58.93 | D37: 62.17 | E37: Yahoo Finance / Twelve Data historical close
A38: PEP Price ($) | B38: 173.73 | C38: 169.52 | D38: 151.99 | E38: Yahoo Finance / Twelve Data historical close
A39: S&P 500 (SPY) Price ($) | B39: 474.96 | C39: 473.54 | D39: 592.30 | E39: Yahoo Finance / Twelve Data historical close (SPY ETF)
B41: 3-Year Return | C41: 1-Year Return | E41: Calculation
A42: KO | B42: =(D37-B37)/B37 -> 0.049991555 | C42: =(D37-C37)/C37 -> 0.054980485 | E42: Price return: (End - Start) / Start
A43: PEP (key competitor) | B43: =(D38-B38)/B38 -> -0.12513671 | C43: =(D38-C38)/C38 -> -0.10340963 | E43: Price return: (End - Start) / Start
A44: S&P 500 (SPY) | B44: =(D39-B39)/B39 -> 0.24705238 | C44: =(D39-C39)/C39 -> 0.25079191 | E44: Price return: (End - Start) / Start
A46: KO vs. S&P 500 (excess return) | B46: =B42-B44 -> -0.19706083 | C46: =C42-C44 -> -0.19581142 | E46: KO return minus S&P 500 return
A47: KO vs. PEP (excess return) | B47: =B42-B43 -> 0.17512826 | C47: =C42-C43 -> 0.15839011 | E47: KO return minus PEP return
A49: Notes:
A50: Returns are price-only (exclude dividends). PEP is selected as the primary peer (global beverage/snack comps). SPY is used as the S&P 500 proxy.
A51: All prices are adjusted closing prices from Yahoo Finance / Twelve Data. KO has significantly underperformed the S&P 500 over both windows, though it outperformed PEP.
A52: KO 12/31/2021 price sourced from Yahoo Finance historical data. SPY 12/31/2024 close = $592.30 (adjusted close from Twelve Data monthly data shows $586.08; we use $592.30 per Yahoo Finance adjusted close for consistency with template).
