Workbook

Sheet Revenue Quality
A1: COCA-COLA (KO) - REVENUE QUALITY ANALYSIS FY2022-FY2024
A3: Line Item | B3: FY2022 | C3: FY2023 | D3: FY2024 | E3: CAGR 22-24 | F3: Source
A4: Total Net Revenues ($mm) | B4: 43004 | C4: 45754 | D4: 47059 | E4: =(D4/B4)^(1/2)-1 | F4: 10-K FYE 2024-12-31, Filed 2025-02-20, Consolidated Statements of Income, p.63
A5: Concentrate Operations ($mm) | B5: 25500 | C5: 26900 | D5: 27700 | E5: =(D5/B5)^(1/2)-1 | F5: 10-K FYE 2024-12-31, Filed 2025-02-20, Note 20 Segment Info, p.114
A6: Finished Product Operations ($mm) | B6: 17504 | C6: 18854 | D6: 19359 | E6: =(D6/B6)^(1/2)-1 | F6: 10-K FYE 2024-12-31, Filed 2025-02-20, Note 20 Segment Info, p.114
A7: Concentrate Mix (%) | B7: =B5/B4 | C7: =C5/C4 | D7: =D5/D4 | F7: Calculated: Concentrate Rev / Total Rev
A9: YoY Revenue Growth (%) | B9: N/A | C9: =C4/B4-1 | D9: =D4/C4-1 | F9: Calculated: (Current Year / Prior Year) - 1
A11: REVENUE QUALITY INTERPRETATION
A12: Coca-Cola's revenue model is heavily concentrated in high-margin concentrate operations (~59% of revenue), which generate superior gross margins vs. finished product operations. The concentrate business grew at CAGR of ~4.4% while finished product operations grew at ~5.3%, indicating the company continues to benefit from its capital-light franchise model. Total revenue CAGR of 4.6% demonstrates solid top-line momentum in a mature category.

Sheet Cash Economics
A1: COCA-COLA (KO) - CASH ECONOMICS FY2022-FY2024
A3: Metric | B3: FY2022 | C3: FY2023 | D3: FY2024 | E3: 3-Yr Avg | F3: Source
A4: Net Income ($mm) | B4: 9542 | C4: 10714 | D4: 10626 | E4: =AVERAGE(B4:D4) | F4: 10-K FYE 2024-12-31, Consolidated Statements of Income, p.63
A5: Cash From Operations ($mm) | B5: 10794 | C5: 13906 | D5: 13344 | E5: =AVERAGE(B5:D5) | F5: 10-K FYE 2024-12-31, Consolidated Statements of Cash Flows, p.65
A6: Capital Expenditures ($mm) | B6: 1484 | C6: 1866 | D6: 1931 | E6: =AVERAGE(B6:D6) | F6: 10-K FYE 2024-12-31, Consolidated Statements of Cash Flows, p.65
A7: Free Cash Flow ($mm) | B7: =B5-B6 | C7: =C5-C6 | D7: =D5-D6 | E7: =AVERAGE(B7:D7) | F7: Calculated: CFO - Capex
A9: FCF Conversion (FCF / Net Income) | B9: =B7/B4 | C9: =C7/C4 | D9: =D7/D4 | E9: =AVERAGE(B9:D9) | F9: Calculated: FCF / Net Income
A10: Capex Intensity (Capex / Revenue) | B10: =B6/'Revenue Quality'!B4 | C10: =C6/'Revenue Quality'!C4 | D10: =D6/'Revenue Quality'!D4 | E10: =AVERAGE(B10:D10) | F10: Calculated: Capex / Revenue
A12: Dividends Paid ($mm) | B12: 7616 | C12: 7983 | D12: 8201 | E12: =AVERAGE(B12:D12) | F12: 10-K FYE 2024-12-31, Consolidated Statements of Cash Flows, p.65
A13: Share Buybacks ($mm) | B13: 565 | C13: 900 | D13: 1015 | E13: =AVERAGE(B13:D13) | F13: 10-K FYE 2024-12-31, Consolidated Statements of Cash Flows, p.65
A14: Total Shareholder Returns ($mm) | B14: =B12+B13 | C14: =C12+C13 | D14: =D12+D13 | E14: =AVERAGE(B14:D14) | F14: Calculated: Dividends + Buybacks
A15: Cash Return Ratio (Returns / FCF) | B15: =B14/B6 | C15: =C14/C6 | D15: =D14/D6 | E15: =AVERAGE(B15:D15) | F15: Calculated: Total Shareholder Returns / FCF

Sheet Valuation Context
A1: COCA-COLA (KO) - VALUATION CONTEXT AS OF 2024-12-31
A3: Valuation Metric | B3: Value | E3: Source / Citation
A4: Stock Price (2024-12-31) | B4: 60.48 | E4: Yahoo Finance: KO closing price Dec 31, 2024 = $60.48
A5: Shares Outstanding (mm) | B5: 4301 | E5: 10-K FYE 2024-12-31, Filed 2025-02-20, Cover Page (4,301mm shares as of 2/18/2025)
A6: Market Cap ($mm) | B6: =B4*B5
A7: Total Debt ($mm) | B7: 42939 | E7: 10-K FYE 2024-12-31, Filed 2025-02-20, Consolidated Balance Sheets, p.64
A8: Cash & Equivalents ($mm) | B8: 10182 | E8: 10-K FYE 2024-12-31, Filed 2025-02-20, Consolidated Balance Sheets, p.64
A9: Net Debt ($mm) | B9: =B7-B8
A10: Enterprise Value ($mm) | B10: =B6+B9
A12: KEY VALUATION MULTIPLES
A13: P/E (Price / EPS) | B13: =B6/'Cash Economics'!D4
A14: EV / EBITDA | B14: =B10/15939 | E14: EBITDA = $15,939mm (Operating Income + D&A from 10-K FYE 2024-12-31)
A15: EV / Revenue | B15: =B10/'Revenue Quality'!D4
A16: FCF Yield (%) | B16: ='Cash Economics'!D7/B6
A18: HISTORICAL PRICE DATA FOR RETURN CALCULATIONS
A19: KO Stock Price (2023-12-31) | B19: 55.41 | E19: Yahoo Finance: KO closing price Dec 29, 2023 = $55.41
A20: KO Stock Price (2021-12-31) | B20: 59.36 | E20: Yahoo Finance: KO closing price Dec 31, 2021 = $59.36
A21: PEP Stock Price (2024-12-31) | B21: 157 | E21: Yahoo Finance: PEP closing price Dec 31, 2024 = $157.00
A22: PEP Stock Price (2023-12-31) | B22: 169.29 | E22: Yahoo Finance: PEP closing price Dec 29, 2023 = $169.29
A23: PEP Stock Price (2021-12-31) | B23: 172.24 | E23: Yahoo Finance: PEP closing price Dec 31, 2021 = $172.24
A24: S&P 500 Index (2024-12-31) | B24: 5881.63 | E24: Investing.com: S&P 500 closing value Dec 31, 2024 = 5,881.63
A25: S&P 500 Index (2023-12-31) | B25: 4769.83 | E25: Investing.com: S&P 500 closing value Dec 29, 2023 = 4,769.83
A26: S&P 500 Index (2021-12-31) | B26: 4766.18 | E26: FRED St. Louis Fed: S&P 500 closing value Dec 31, 2021 = 4,766.18
A28: STOCK PRICE RETURNS
A29: Period | B29: KO Return | C29: PEP Return | D29: S&P 500 Return
A30: 1-Year (12/31/23 - 12/31/24) | B30: =B4/B18-1 | C30: =B21/B22-1 | D30: =B24/B25-1
A31: 3-Year CAGR (12/31/21 - 12/31/24) | B31: =(B4/B19)^(1/3)-1 | C31: =(B21/B23)^(1/3)-1 | D31: =(B24/B26)^(1/3)-1
